{"chipID": "C127E", "deviceID": "23-24", "dataFolder": "data/", "plotsFolder": "CurrentPlots/", "postFigures": true, "NPLC": 1, "GateSweep": {"saveFileName": "GateSweep", "runDataPoints": 600, "complianceCurrent": 0.0001, "drainVoltageSetPoint": 0.5, "gateVoltageMinimum": -15.0, "gateVoltageMaximum": 15.0}, "BurnOut": {"saveFileName": "BurnOut", "runDataPoints": 1000, "complianceCurrent": 0.002, "thresholdProportion": 0.8, "minimumAppliedDrainVoltage": 0.9, "gateVoltageSetPoint": 15.0, "drainVoltageMaxPoint": 10, "drainVoltagePlateaus": 10}, "AutoBurnOut": {"targetOnOffRatio": 300, "limitBurnOutsAllowed": 8, "limitOnOffRatioDegradation": 0.7}, "StaticBias": {"saveFileName": "StaticBias", "runDataPoints": 360, "complianceCurrent": 0.0001, "startUpSettlingDelay": 2, "biasTime": 3600, "gateVoltageSetPoint": -15.0, "drainVoltageSetPoint": 1.0, "groundGateWhenDone": false, "groundDrainWhenDone": false}, "AutoGateSweep": {"numberOfSweeps": 24, "applyStaticBiasBetweenSweeps": true}, "AutoStaticBias": {"numberOfStaticBiases": 24, "applyGateSweepBetweenBiases": false, "delayBetweenBiases": 0, "numberOfBiasesBetweenIncrements": 6, "incrementStaticDrainVoltage": 0.2, "incrementStaticGateVoltage": 0}, "DeviceHistory": {"plotGateSweeps": true, "plotBurnOuts": true, "plotStaticBias": true, "saveFiguresGenerated": true, "excludeDataBeforeJSONIndex": 0, "excludeDataAfterJSONIndex": Infinity, "excludeDataBeforeJSONExperimentNumber": 0, "excludeDataAfterJSONExperimentNumber": Infinity, "showOnlySuccessfulBurns": false}, "ChipHistory": {}, "runType": "GateSweep", "deviceDirectory": "data/C127E/23-24/", "startIndexes": {"index": 0, "experimentNumber": 1}, "endIndexes": {"index": 1, "experimentNumber": 1}}
{"chipID": "C127E", "deviceID": "23-24", "dataFolder": "data/", "plotsFolder": "CurrentPlots/", "postFigures": true, "NPLC": 1, "GateSweep": {"saveFileName": "GateSweep", "runDataPoints": 600, "complianceCurrent": 0.0001, "drainVoltageSetPoint": 0.5, "gateVoltageMinimum": -15.0, "gateVoltageMaximum": 15.0}, "BurnOut": {"saveFileName": "BurnOut", "runDataPoints": 1000, "complianceCurrent": 0.002, "thresholdProportion": 0.8, "minimumAppliedDrainVoltage": 0.9, "gateVoltageSetPoint": 15.0, "drainVoltageMaxPoint": 10, "drainVoltagePlateaus": 10}, "AutoBurnOut": {"targetOnOffRatio": 300, "limitBurnOutsAllowed": 8, "limitOnOffRatioDegradation": 0.7}, "StaticBias": {"saveFileName": "StaticBias", "runDataPoints": 360, "complianceCurrent": 0.0001, "startUpSettlingDelay": 2, "biasTime": 3600, "gateVoltageSetPoint": -15.0, "drainVoltageSetPoint": 1.0, "groundGateWhenDone": false, "groundDrainWhenDone": false}, "AutoGateSweep": {"numberOfSweeps": 24, "applyStaticBiasBetweenSweeps": true}, "AutoStaticBias": {"numberOfStaticBiases": 24, "applyGateSweepBetweenBiases": false, "delayBetweenBiases": 0, "numberOfBiasesBetweenIncrements": 6, "incrementStaticDrainVoltage": 0.2, "incrementStaticGateVoltage": 0}, "DeviceHistory": {"plotGateSweeps": true, "plotBurnOuts": true, "plotStaticBias": false, "saveFiguresGenerated": true, "excludeDataBeforeJSONIndex": 0, "excludeDataAfterJSONIndex": Infinity, "excludeDataBeforeJSONExperimentNumber": 4, "excludeDataAfterJSONExperimentNumber": 4, "showOnlySuccessfulBurns": false}, "ChipHistory": {}, "runType": "AutoBurnOut", "deviceDirectory": "data/C127E/23-24/", "startIndexes": {"index": 5, "experimentNumber": 4}, "endIndexes": {"index": 8, "experimentNumber": 4}}
{"chipID": "C127E", "deviceID": "23-24", "dataFolder": "data/", "plotsFolder": "CurrentPlots/", "postFigures": true, "NPLC": 1, "GateSweep": {"saveFileName": "GateSweep", "runDataPoints": 600, "complianceCurrent": 0.0001, "drainVoltageSetPoint": 0.5, "gateVoltageMinimum": -15.0, "gateVoltageMaximum": 15.0}, "BurnOut": {"saveFileName": "BurnOut", "runDataPoints": 1000, "complianceCurrent": 0.002, "thresholdProportion": 0.8, "minimumAppliedDrainVoltage": 0.9, "gateVoltageSetPoint": 15.0, "drainVoltageMaxPoint": 10, "drainVoltagePlateaus": 10}, "AutoBurnOut": {"targetOnOffRatio": 300, "limitBurnOutsAllowed": 8, "limitOnOffRatioDegradation": 0.7}, "StaticBias": {"saveFileName": "StaticBias", "runDataPoints": 360, "complianceCurrent": 0.0001, "startUpSettlingDelay": 2, "biasTime": 3600, "gateVoltageSetPoint": -15.0, "drainVoltageSetPoint": 1.0, "groundGateWhenDone": false, "groundDrainWhenDone": false}, "AutoGateSweep": {"numberOfSweeps": 24, "applyStaticBiasBetweenSweeps": true}, "AutoStaticBias": {"numberOfStaticBiases": 24, "applyGateSweepBetweenBiases": false, "delayBetweenBiases": 0, "numberOfBiasesBetweenIncrements": 6, "incrementStaticDrainVoltage": 0.2, "incrementStaticGateVoltage": 0}, "DeviceHistory": {"plotGateSweeps": true, "plotBurnOuts": true, "plotStaticBias": false, "saveFiguresGenerated": true, "excludeDataBeforeJSONIndex": 0, "excludeDataAfterJSONIndex": Infinity, "excludeDataBeforeJSONExperimentNumber": 4, "excludeDataAfterJSONExperimentNumber": 4, "showOnlySuccessfulBurns": false}, "ChipHistory": {}, "runType": "BurnOut", "deviceDirectory": "data/C127E/23-24/", "startIndexes": {"index": 8, "experimentNumber": 5}, "endIndexes": {"index": 9, "experimentNumber": 5}}
{"chipID": "C127E", "deviceID": "23-24", "dataFolder": "data/", "plotsFolder": "CurrentPlots/", "postFigures": true, "NPLC": 1, "GateSweep": {"saveFileName": "GateSweep", "runDataPoints": 600, "complianceCurrent": 0.0001, "drainVoltageSetPoint": 0.5, "gateVoltageMinimum": -15.0, "gateVoltageMaximum": 15.0}, "BurnOut": {"saveFileName": "BurnOut", "runDataPoints": 1000, "complianceCurrent": 0.002, "thresholdProportion": 0.8, "minimumAppliedDrainVoltage": 0.9, "gateVoltageSetPoint": 15.0, "drainVoltageMaxPoint": 10, "drainVoltagePlateaus": 10}, "AutoBurnOut": {"targetOnOffRatio": 300, "limitBurnOutsAllowed": 8, "limitOnOffRatioDegradation": 0.7}, "StaticBias": {"saveFileName": "StaticBias", "runDataPoints": 360, "complianceCurrent": 0.0001, "startUpSettlingDelay": 2, "biasTime": 3600, "gateVoltageSetPoint": -15.0, "drainVoltageSetPoint": 1.0, "groundGateWhenDone": false, "groundDrainWhenDone": false}, "AutoGateSweep": {"numberOfSweeps": 24, "applyStaticBiasBetweenSweeps": true}, "AutoStaticBias": {"numberOfStaticBiases": 24, "applyGateSweepBetweenBiases": false, "delayBetweenBiases": 0, "numberOfBiasesBetweenIncrements": 6, "incrementStaticDrainVoltage": 0.2, "incrementStaticGateVoltage": 0}, "DeviceHistory": {"plotGateSweeps": true, "plotBurnOuts": true, "plotStaticBias": false, "saveFiguresGenerated": true, "excludeDataBeforeJSONIndex": 0, "excludeDataAfterJSONIndex": Infinity, "excludeDataBeforeJSONExperimentNumber": 4, "excludeDataAfterJSONExperimentNumber": 4, "showOnlySuccessfulBurns": false}, "ChipHistory": {}, "runType": "GateSweep", "deviceDirectory": "data/C127E/23-24/", "startIndexes": {"index": 9, "experimentNumber": 6}, "endIndexes": {"index": 10, "experimentNumber": 6}}
{"chipID": "C127E", "deviceID": "23-24", "dataFolder": "data/", "plotsFolder": "CurrentPlots/", "postFigures": true, "NPLC": 1, "GateSweep": {"saveFileName": "GateSweep", "runDataPoints": 600, "complianceCurrent": 0.0001, "drainVoltageSetPoint": 0.5, "gateVoltageMinimum": -15.0, "gateVoltageMaximum": 15.0}, "BurnOut": {"saveFileName": "BurnOut", "runDataPoints": 1000, "complianceCurrent": 0.002, "thresholdProportion": 0.8, "minimumAppliedDrainVoltage": 0.9, "gateVoltageSetPoint": 15.0, "drainVoltageMaxPoint": 10, "drainVoltagePlateaus": 10}, "AutoBurnOut": {"targetOnOffRatio": 300, "limitBurnOutsAllowed": 8, "limitOnOffRatioDegradation": 0.7}, "StaticBias": {"saveFileName": "StaticBias", "runDataPoints": 360, "complianceCurrent": 0.0001, "startUpSettlingDelay": 2, "biasTime": 3600, "gateVoltageSetPoint": -15.0, "drainVoltageSetPoint": 1.5999999999999999, "groundGateWhenDone": false, "groundDrainWhenDone": false}, "AutoGateSweep": {"numberOfSweeps": 24, "applyStaticBiasBetweenSweeps": true}, "AutoStaticBias": {"numberOfStaticBiases": 24, "applyGateSweepBetweenBiases": false, "delayBetweenBiases": 0, "numberOfBiasesBetweenIncrements": 8, "incrementStaticDrainVoltage": 0.2, "incrementStaticGateVoltage": 0}, "DeviceHistory": {"plotGateSweeps": false, "plotBurnOuts": false, "plotStaticBias": true, "saveFiguresGenerated": true, "excludeDataBeforeJSONIndex": 0, "excludeDataAfterJSONIndex": Infinity, "excludeDataBeforeJSONExperimentNumber": 7, "excludeDataAfterJSONExperimentNumber": 7, "showOnlySuccessfulBurns": false}, "ChipHistory": {}, "runType": "AutoStaticBias", "deviceDirectory": "data/C127E/23-24/", "startIndexes": {"index": 10, "experimentNumber": 7}, "endIndexes": {"index": 34, "experimentNumber": 7}}
{"chipID": "C127E", "deviceID": "23-24", "dataFolder": "data/", "plotsFolder": "CurrentPlots/", "postFigures": true, "NPLC": 1, "GateSweep": {"saveFileName": "GateSweep", "runDataPoints": 600, "complianceCurrent": 0.0001, "drainVoltageSetPoint": 0.5, "gateVoltageMinimum": -15.0, "gateVoltageMaximum": 15.0}, "BurnOut": {"saveFileName": "BurnOut", "runDataPoints": 1000, "complianceCurrent": 0.002, "thresholdProportion": 0.8, "minimumAppliedDrainVoltage": 0.9, "gateVoltageSetPoint": 15.0, "drainVoltageMaxPoint": 10, "drainVoltagePlateaus": 10}, "AutoBurnOut": {"targetOnOffRatio": 300, "limitBurnOutsAllowed": 8, "limitOnOffRatioDegradation": 0.7}, "StaticBias": {"saveFileName": "StaticBias", "runDataPoints": 360, "complianceCurrent": 0.0001, "startUpSettlingDelay": 2, "biasTime": 3600, "gateVoltageSetPoint": -15.0, "drainVoltageSetPoint": 1.0, "groundGateWhenDone": false, "groundDrainWhenDone": false}, "AutoGateSweep": {"numberOfSweeps": 24, "applyStaticBiasBetweenSweeps": true}, "AutoStaticBias": {"numberOfStaticBiases": 24, "delayBetweenBiases": 30, "applyGateSweepBetweenBiases": false, "numberOfBiasesBetweenIncrements": 6, "incrementStaticDrainVoltage": 0, "incrementStaticGateVoltage": 0, "incrementDelayBetweenBiases": 0, "incrementallyToggleGrounding": true}, "DeviceHistory": {"plotGateSweeps": true, "plotBurnOuts": true, "plotStaticBias": true, "saveFiguresGenerated": true, "excludeDataBeforeJSONIndex": 0, "excludeDataAfterJSONIndex": Infinity, "excludeDataBeforeJSONExperimentNumber": 0, "excludeDataAfterJSONExperimentNumber": Infinity, "showOnlySuccessfulBurns": false}, "ChipHistory": {}, "runType": "GateSweep", "deviceDirectory": "data/C127E/23-24/", "startIndexes": {"index": 34, "experimentNumber": 8}, "endIndexes": {"index": 35, "experimentNumber": 8}}
{"chipID": "C127E", "deviceID": "23-24", "dataFolder": "data/", "plotsFolder": "CurrentPlots/", "postFigures": true, "NPLC": 1, "GateSweep": {"saveFileName": "GateSweep", "runDataPoints": 600, "complianceCurrent": 0.0001, "drainVoltageSetPoint": 0.5, "gateVoltageMinimum": -15.0, "gateVoltageMaximum": 15.0}, "BurnOut": {"saveFileName": "BurnOut", "runDataPoints": 1000, "complianceCurrent": 0.002, "thresholdProportion": 0.8, "minimumAppliedDrainVoltage": 0.9, "gateVoltageSetPoint": 15.0, "drainVoltageMaxPoint": 10, "drainVoltagePlateaus": 10}, "AutoBurnOut": {"targetOnOffRatio": 300, "limitBurnOutsAllowed": 8, "limitOnOffRatioDegradation": 0.7}, "StaticBias": {"saveFileName": "StaticBias", "runDataPoints": 360, "complianceCurrent": 0.0001, "startUpSettlingDelay": 2, "biasTime": 3600, "gateVoltageSetPoint": -15.0, "drainVoltageSetPoint": 1.0, "groundGateWhenDone": false, "groundDrainWhenDone": false}, "AutoGateSweep": {"numberOfSweeps": 24, "applyStaticBiasBetweenSweeps": true}, "AutoStaticBias": {"numberOfStaticBiases": 24, "delayBetweenBiases": 30, "applyGateSweepBetweenBiases": false, "numberOfBiasesBetweenIncrements": 6, "incrementStaticDrainVoltage": 0, "incrementStaticGateVoltage": 0, "incrementDelayBetweenBiases": 0, "incrementallyToggleGrounding": true}, "DeviceHistory": {"plotGateSweeps": false, "plotBurnOuts": false, "plotStaticBias": true, "saveFiguresGenerated": true, "excludeDataBeforeJSONIndex": 0, "excludeDataAfterJSONIndex": Infinity, "excludeDataBeforeJSONExperimentNumber": 9, "excludeDataAfterJSONExperimentNumber": 9, "showOnlySuccessfulBurns": false}, "ChipHistory": {}, "runType": "AutoStaticBias", "deviceDirectory": "data/C127E/23-24/", "startIndexes": {"index": 35, "experimentNumber": 9}, "endIndexes": {"index": 59, "experimentNumber": 9}}
{"chipID": "C127E", "deviceID": "23-24", "dataFolder": "data/", "plotsFolder": "CurrentPlots/", "postFigures": true, "NPLC": 1, "GateSweep": {"saveFileName": "GateSweep", "runDataPoints": 600, "complianceCurrent": 0.0001, "drainVoltageSetPoint": 0.5, "gateVoltageMinimum": -15.0, "gateVoltageMaximum": 15.0}, "BurnOut": {"saveFileName": "BurnOut", "runDataPoints": 1000, "complianceCurrent": 0.002, "thresholdProportion": 0.8, "minimumAppliedDrainVoltage": 0.9, "gateVoltageSetPoint": 15.0, "drainVoltageMaxPoint": 10, "drainVoltagePlateaus": 10}, "AutoBurnOut": {"targetOnOffRatio": 300, "limitBurnOutsAllowed": 8, "limitOnOffRatioDegradation": 0.7}, "StaticBias": {"saveFileName": "StaticBias", "runDataPoints": 360, "complianceCurrent": 0.0001, "startUpSettlingDelay": 2, "biasTime": 3600, "gateVoltageSetPoint": -15.0, "drainVoltageSetPoint": 1.0, "groundGateWhenDone": false, "groundDrainWhenDone": false}, "AutoGateSweep": {"numberOfSweeps": 24, "applyStaticBiasBetweenSweeps": true}, "AutoStaticBias": {"numberOfStaticBiases": 24, "delayBetweenBiases": 30, "applyGateSweepBetweenBiases": false, "numberOfBiasesBetweenIncrements": 6, "incrementStaticDrainVoltage": 0, "incrementStaticGateVoltage": 0, "incrementDelayBetweenBiases": 0, "incrementallyToggleGrounding": true}, "DeviceHistory": {"plotGateSweeps": true, "plotBurnOuts": true, "plotStaticBias": true, "saveFiguresGenerated": true, "excludeDataBeforeJSONIndex": 0, "excludeDataAfterJSONIndex": Infinity, "excludeDataBeforeJSONExperimentNumber": 0, "excludeDataAfterJSONExperimentNumber": Infinity, "showOnlySuccessfulBurns": false}, "ChipHistory": {}, "runType": "GateSweep", "deviceDirectory": "data/C127E/23-24/", "startIndexes": {"index": 59, "experimentNumber": 10}, "endIndexes": {"index": 60, "experimentNumber": 10}}
{"chipID": "C127E", "deviceID": "23-24", "dataFolder": "data/", "plotsFolder": "CurrentPlots/", "postFigures": true, "NPLC": 1, "GateSweep": {"saveFileName": "GateSweep", "runDataPoints": 600, "complianceCurrent": 0.0001, "drainVoltageSetPoint": 0.5, "gateVoltageMinimum": -15.0, "gateVoltageMaximum": 15.0}, "BurnOut": {"saveFileName": "BurnOut", "runDataPoints": 1000, "complianceCurrent": 0.002, "thresholdProportion": 0.8, "minimumAppliedDrainVoltage": 0.9, "gateVoltageSetPoint": 15.0, "drainVoltageMaxPoint": 10, "drainVoltagePlateaus": 10}, "AutoBurnOut": {"targetOnOffRatio": 300, "limitBurnOutsAllowed": 8, "limitOnOffRatioDegradation": 0.7}, "StaticBias": {"saveFileName": "StaticBias", "runDataPoints": 360, "complianceCurrent": 0.0001, "startUpSettlingDelay": 2, "biasTime": 3600, "gateVoltageSetPoint": -15.0, "drainVoltageSetPoint": 1.0, "groundGateWhenDone": true, "groundDrainWhenDone": true}, "AutoGateSweep": {"numberOfSweeps": 24, "applyStaticBiasBetweenSweeps": true}, "AutoStaticBias": {"numberOfStaticBiases": 24, "delayBetweenBiases": 0, "applyGateSweepBetweenBiases": false, "numberOfBiasesBetweenIncrements": 1, "incrementStaticDrainVoltage": 0, "incrementStaticGateVoltage": 0, "incrementDelayBetweenBiases": 1, "incrementallyToggleGrounding": false}, "DeviceHistory": {"plotGateSweeps": true, "plotBurnOuts": true, "plotStaticBias": true, "saveFiguresGenerated": true, "excludeDataBeforeJSONIndex": 0, "excludeDataAfterJSONIndex": Infinity, "excludeDataBeforeJSONExperimentNumber": 0, "excludeDataAfterJSONExperimentNumber": Infinity, "showOnlySuccessfulBurns": false}, "ChipHistory": {}, "runType": "GateSweep", "deviceDirectory": "data/C127E/23-24/", "startIndexes": {"index": 60, "experimentNumber": 11}, "endIndexes": {"index": 61, "experimentNumber": 11}}
